<PAMDataset>
  <PAMRasterBand band="1">
    <Histograms>
      <HistItem>
        <HistMin>-0.498046875</HistMin>
        <HistMax>255.498046875</HistMax>
        <BucketCount>256</BucketCount>
        <IncludeOutOfRange>0</IncludeOutOfRange>
        <Approximate>1</Approximate>
        <HistCounts>0|0|0|0|0|0|0|0|0|0|3|5|3|6|7|9|13|19|14|29|21|18|20|28|24|22|19|13|14|8|10|7|9|7|7|4|6|7|4|5|6|4|2|6|4|20|21|35|53|69|68|68|67|73|71|80|121|157|173|169|233|307|379|465|548|674|743|833|893|954|902|886|875|826|843|853|854|855|822|775|733|723|756|775|765|759|838|805|858|837|877|985|1036|1020|1011|986|1112|1157|1184|1297|1243|1215|1200|1162|1275|1399|1496|1640|1728|1611|1700|1763|1783|1853|1894|1936|1964|2088|2010|1947|1889|1895|2031|2093|2182|2179|2111|2154|2024|1996|1918|1822|1702|1799|1767|1940|1902|1846|1860|1664|1565|1482|1364|1264|1317|1329|1328|1324|1302|1301|1301|1201|1108|1076|1028|1070|1074|1171|1112|1083|1038|1024|945|1049|997|1057|973|999|898|907|830|914|869|865|880|848|786|774|799|812|842|834|794|818|706|688|720|688|737|665|641|618|642|658|610|617|561|572|548|504|564|519|483|446|437|393|437|401|430|366|387|352|342|342|356|321|332|321|280|309|281|290|266|284|282|202|269|222|199|186|186|173|139|136|134|159|124|124|99|98|94|90|108|110|97|122|103|92|106|62|76|109|155|355|855|71922</HistCounts>
      </HistItem>
    </Histograms>
    <Metadata domain="IMAGE_STRUCTURE">
      <MDI key="COMPRESSION">JPEG</MDI>
    </Metadata>
  </PAMRasterBand>
</PAMDataset>
